ament_cmake_flake8/_dummy.cpython-314t-x86_64-linux-gnu.so
ros_ament_cmake_flake8-0.17.3.data/data/share/ament_cmake_flake8/local_setup.bash
ros_ament_cmake_flake8-0.17.3.data/data/share/ament_cmake_flake8/local_setup.dsv
ros_ament_cmake_flake8-0.17.3.data/data/share/ament_cmake_flake8/local_setup.sh
ros_ament_cmake_flake8-0.17.3.data/data/share/ament_cmake_flake8/local_setup.zsh
ros_ament_cmake_flake8-0.17.3.data/data/share/ament_cmake_flake8/package.dsv
ros_ament_cmake_flake8-0.17.3.data/data/share/ament_cmake_flake8/package.xml
ros_ament_cmake_flake8-0.17.3.data/data/share/ament_cmake_flake8/cmake/ament_cmake_flake8-extras.cmake
ros_ament_cmake_flake8-0.17.3.data/data/share/ament_cmake_flake8/cmake/ament_cmake_flake8Config-version.cmake
ros_ament_cmake_flake8-0.17.3.data/data/share/ament_cmake_flake8/cmake/ament_cmake_flake8Config.cmake
ros_ament_cmake_flake8-0.17.3.data/data/share/ament_cmake_flake8/cmake/ament_cmake_flake8_lint_hook.cmake
ros_ament_cmake_flake8-0.17.3.data/data/share/ament_cmake_flake8/cmake/ament_flake8.cmake
ros_ament_cmake_flake8-0.17.3.data/data/share/ament_cmake_flake8/environment/ament_prefix_path.dsv
ros_ament_cmake_flake8-0.17.3.data/data/share/ament_cmake_flake8/environment/ament_prefix_path.sh
ros_ament_cmake_flake8-0.17.3.data/data/share/ament_cmake_flake8/environment/path.dsv
ros_ament_cmake_flake8-0.17.3.data/data/share/ament_cmake_flake8/environment/path.sh
ros_ament_cmake_flake8-0.17.3.data/data/share/ament_index/resource_index/package_run_dependencies/ament_cmake_flake8
ros_ament_cmake_flake8-0.17.3.data/data/share/ament_index/resource_index/packages/ament_cmake_flake8
ros_ament_cmake_flake8-0.17.3.data/data/share/ament_index/resource_index/parent_prefix_path/ament_cmake_flake8
ros_ament_cmake_flake8-0.17.3.dist-info/METADATA
ros_ament_cmake_flake8-0.17.3.dist-info/WHEEL
ros_ament_cmake_flake8-0.17.3.dist-info/top_level.txt
ros_ament_cmake_flake8-0.17.3.dist-info/RECORD
