Metadata-Version: 2.4
Name: ros-ament-cmake-flake8
Version: 0.17.3
Summary: Wheel for the ament_cmake_flake8 (ros-ament-cmake-flake8) ROS 2 package.
Dynamic: description
Dynamic: description-content-type
Dynamic: summary
